{
  "metadata": {
    "rules_path": "G:\\Develop\\python\\LME-Testing\\.tmp_rule_workflow_sessions\\20260505T151304Z\\artifacts\\im_hk_v14\\rule_review\\reviewed_semantic_rules.json",
    "maker_cases_path": "G:\\Develop\\python\\LME-Testing\\.tmp_rule_workflow_sessions\\20260505T151304Z\\generated_cases\\20260505T151318Z\\maker\\20260505T151318Z\\maker_cases.jsonl",
    "checker_reviews_path": "G:\\Develop\\python\\LME-Testing\\.tmp_rule_workflow_sessions\\20260505T151304Z\\generated_cases\\20260505T151318Z\\checker\\20260505T152805Z\\checker_reviews.jsonl",
    "latest_review_path": ".tmp_rule_workflow_sessions\\20260505T151304Z\\scenario_review_sessions\\20260505T153951Z\\iterations\\000\\reviews\\human_reviews_latest.json",
    "current_report_path": ".tmp_rule_workflow_sessions\\20260505T151304Z\\scenario_review_sessions\\20260505T153951Z\\iterations\\000\\report\\report.html"
  },
  "reviews": [
    {
      "case_id": "TC-SR-IMHK-3_2_4_2-01-positive-01",
      "semantic_rule_id": "SR-IMHK-3_2_4_2-01",
      "review_decision": "rewrite",
      "human_comment": "",
      "issue_types": []
    },
    {
      "case_id": "TC-SR-IMHK-3_2_4_2-01-boundary-01",
      "semantic_rule_id": "SR-IMHK-3_2_4_2-01",
      "review_decision": "rewrite",
      "human_comment": "",
      "issue_types": []
    },
    {
      "case_id": "TC-SR-IMHK-3_2_4_2-01-data_validation-01",
      "semantic_rule_id": "SR-IMHK-3_2_4_2-01",
      "review_decision": "pending",
      "human_comment": "",
      "issue_types": []
    },
    {
      "case_id": "TC-SR-IMHK-3_2_5_1-01-positive-01",
      "semantic_rule_id": "SR-IMHK-3_2_5_1-01",
      "review_decision": "pending",
      "human_comment": "",
      "issue_types": []
    },
    {
      "case_id": "TC-SR-IMHK-3_2_5_1-01-boundary-01",
      "semantic_rule_id": "SR-IMHK-3_2_5_1-01",
      "review_decision": "pending",
      "human_comment": "",
      "issue_types": []
    },
    {
      "case_id": "TC-SR-IMHK-3_2_5_1-01-data_validation-01",
      "semantic_rule_id": "SR-IMHK-3_2_5_1-01",
      "review_decision": "pending",
      "human_comment": "",
      "issue_types": []
    },
    {
      "case_id": "TC-SR-IMHK-3_2_5_2-01-positive-01",
      "semantic_rule_id": "SR-IMHK-3_2_5_2-01",
      "review_decision": "pending",
      "human_comment": "",
      "issue_types": []
    },
    {
      "case_id": "TC-SR-IMHK-3_2_5_2-01-boundary-01",
      "semantic_rule_id": "SR-IMHK-3_2_5_2-01",
      "review_decision": "pending",
      "human_comment": "",
      "issue_types": []
    },
    {
      "case_id": "TC-SR-IMHK-3_2_5_2-01-data_validation-01",
      "semantic_rule_id": "SR-IMHK-3_2_5_2-01",
      "review_decision": "pending",
      "human_comment": "",
      "issue_types": []
    },
    {
      "case_id": "TC-SR-IMHK-3_2_5_3-01-positive-01",
      "semantic_rule_id": "SR-IMHK-3_2_5_3-01",
      "review_decision": "pending",
      "human_comment": "",
      "issue_types": []
    },
    {
      "case_id": "TC-SR-IMHK-3_2_5_3-01-boundary-01",
      "semantic_rule_id": "SR-IMHK-3_2_5_3-01",
      "review_decision": "pending",
      "human_comment": "",
      "issue_types": []
    },
    {
      "case_id": "TC-SR-IMHK-3_2_5_3-01-data_validation-01",
      "semantic_rule_id": "SR-IMHK-3_2_5_3-01",
      "review_decision": "pending",
      "human_comment": "",
      "issue_types": []
    },
    {
      "case_id": "TC-SR-IMHK-3_2_8-01-positive-01",
      "semantic_rule_id": "SR-IMHK-3_2_8-01",
      "review_decision": "pending",
      "human_comment": "",
      "issue_types": []
    },
    {
      "case_id": "TC-SR-IMHK-3_2_8-01-boundary-01",
      "semantic_rule_id": "SR-IMHK-3_2_8-01",
      "review_decision": "pending",
      "human_comment": "",
      "issue_types": []
    },
    {
      "case_id": "TC-SR-IMHK-3_2_8-01-data_validation-01",
      "semantic_rule_id": "SR-IMHK-3_2_8-01",
      "review_decision": "pending",
      "human_comment": "",
      "issue_types": []
    }
  ]
}